betalytics/__init__.py
betalytics/common/__init__.py
betalytics/common/math_utils.py
betalytics/common/test_utils.py
betalytics/soccer/__init__.py
betalytics/soccer/const.py
betalytics/soccer/finance_management/__init__.py
betalytics/soccer/finance_management/all.py
betalytics/soccer/loader/__init__.py
betalytics/soccer/loader/football_data_loader.py
betalytics/soccer/performance/__init__.py
betalytics/soccer/stats/__init__.py
betalytics/soccer/stats/team_ratings.py
betalytics/soccer/strategies/__init__.py
betalytics/soccer/strategies/all.py
betalytics/soccer/utilities/__init__.py
tests/__init__.py
tests/integration/__init__.py
tests/unit/__init__.py
tests/unit/test_soccer_data_loader.py
betalytics-0.3.dist-info/METADATA
betalytics-0.3.dist-info/WHEEL
betalytics-0.3.dist-info/entry_points.txt
betalytics-0.3.dist-info/top_level.txt
betalytics-0.3.dist-info/RECORD
